my_train/__init__.py
my_train/train_rnn.py
my_train/trainer.py
my_trainer-0.1.4.dist-info/METADATA
my_trainer-0.1.4.dist-info/WHEEL
my_trainer-0.1.4.dist-info/entry_points.txt
my_trainer-0.1.4.dist-info/RECORD
